{
  "id": "playground-file-upload",
  "name": "playground-file-upload",
  "title": "playground: model-based file upload",
  "description": "",
  "status": "in_progress",
  "dev_type": null,
  "scope": null,
  "package": null,
  "priority": "P2",
  "creator": "u2",
  "assignee": "u2",
  "createdAt": "2026-05-13",
  "completedAt": null,
  "branch": null,
  "base_branch": "master",
  "worktree_path": null,
  "commit": null,
  "pr_url": null,
  "subtasks": [],
  "children": [],
  "parent": null,
  "relatedFiles": [],
  "notes": "",
  "meta": {
    "prd_status": "confirmed",
    "workflow": {
      "version": 1,
      "current_step": "awaiting_implement",
      "vcs": {
        "kind": "git",
        "commit_required": true
      },
      "implement": {
        "dispatched_at": null,
        "completed_at": null
      },
      "check": {
        "completed_at": null,
        "fingerprint": null,
        "head": null
      },
      "spec_update": {
        "reviewed_at": null,
        "result": null
      },
      "commit": {
        "hash": null,
        "recorded_at": null
      }
    }
  }
}